dmt_auto_gui/__init__.py
dmt_auto_gui/autogui.py
dmt_auto_gui/gui_controller.py
dmt_auto_gui/keyboard_controller.py
dmt_auto_gui/logger.py
dmt_auto_gui/models/__init__.py
dmt_auto_gui/models/model_autogui_error.py
dmt_auto_gui/models/model_autogui_reponse.py
dmt_auto_gui/models/model_response.py
dmt_auto_gui/screen_controller.py
dmt_auto_gui/system_controller.py
dmt_auto_gui-0.1.22.dist-info/METADATA
dmt_auto_gui-0.1.22.dist-info/WHEEL
dmt_auto_gui-0.1.22.dist-info/RECORD
